README.md
setup.cfg
setup.py
zcfd/__init__.py
zcfd/zCFDSolver.py
zcfd/solvers/DGExplicitSolver.py
zcfd/solvers/EulerSolver.py
zcfd/solvers/ExplicitSolver.py
zcfd/solvers/TurbulentSolver.py
zcfd/solvers/ViscousSolver.py
zcfd/solvers/__init__.py
zcfd/solvers/cfl.py
zcfd/solvers/utils/DGNodalLocations.py
zcfd/solvers/utils/RungeKutta.py
zcfd/solvers/utils/RuntimeLoader.py
zcfd/solvers/utils/__init__.py
zcfd/utils/Logger.py
zcfd/utils/Parameters.py
zcfd/utils/TimeSpent.py
zcfd/utils/__init__.py
zcfd/utils/commandline.py
zcfd/utils/config.py
zcfd_validate/__init__.py
zcfd_validate.egg-info/PKG-INFO
zcfd_validate.egg-info/SOURCES.txt
zcfd_validate.egg-info/dependency_links.txt
zcfd_validate.egg-info/requires.txt
zcfd_validate.egg-info/top_level.txt
zcfd_validate.egg-info/zip-safe