Metadata-Version: 1.1
Name: zcfd-validate
Version: 2018.7.60.post2
Summary: Validation tools for validating a zCFD input file
Home-page: https://zcfd.zenotech.com
Author: Zenotech
Author-email: support@zenotech.com
License: BSD 3-Clause License
Keywords: zCFD
Platform: UNKNOWN
Classifier: Development Status :: 3 - Alpha
Classifier: Programming Language :: Python :: 2.7
